Metadata-Version: 2.1
Name: odoo14-addon-helpdesk_mgmt_timesheet
Version: 14.0.1.3.0
Summary: Add HR Timesheet to the tickets for Helpdesk Management.
Home-page: https://github.com/OCA/helpdesk
Author: Aresoltec Canarias, Punt Sistemes, SDi Soluciones Digitales, Solvos, Odoo Community Association (OCA)
Author-email: support@odoo-community.org
License: AGPL-3
Classifier: Programming Language :: Python
Classifier: Framework :: Odoo
Classifier: Framework :: Odoo :: 14.0
Classifier: License :: OSI Approved :: GNU Affero General Public License v3
Requires-Python: >=3.6
Requires-Dist: odoo14-addon-helpdesk-mgmt-project
Requires-Dist: odoo14-addon-project-timesheet-time-control
Requires-Dist: odoo <14.1dev,>=14.0a
